{
   "count":6,
   "previous":null,
   "results":[
      {
        "name": "Colorboys Vol.1",
        "imgURL": "https://f4.bcbits.com/img/a0348918002_10.jpg",
        "artist": "Colorboys"
        "date": "2019",
      },
      {
        "name": "Colorboys Vol.2",
        "imgURL": "https://f4.bcbits.com/img/a3625594575_10.jpg",
        "artist": "Colorboys"
        "date": "2020",
      },
      {
        "name": "escape",
        "imgURL": "https://f4.bcbits.com/img/a2430958973_10.jpg",
        "artist": "97Special"
        "date": "2020",
      },
      {
        "name": "Flowers In The Trap 2.5",
        "imgURL": "https://f4.bcbits.com/img/a0533983056_10.jpg",
        "artist": "Shogonodo"
        "date": "2019",
      },
      {
        "name": "reverie",
        "imgURL": "https://f4.bcbits.com/img/a0888274754_10.jpg",
        "artist": "Shogonodo"
        "date": "2018",
      },
      {
        "name": "Orikami & Feels Compilation",
        "imgURL": "https://f4.bcbits.com/img/a1726818318_10.jpg",
        "artist": "Orikami Records"
        "date": "2018",
      }
   ]
}
